[
    {
        "title": "Song 1",
        "artist": "Artist 1",
        "url": "https://your-username.github.io/your-repository/song1.mp3"
    },
    {
        "title": "Song 2",
        "artist": "Artist 2",
        "url": "https://your-username.github.io/your-repository/song2.mp3"
    },
    {
        "title": "Song 3",
        "artist": "Artist 3",
        "url": "https://your-username.github.io/your-repository/song2.mp3"
    },
    {
        "title": "Song 4",
        "artist": "Artist 4",
        "url": "https://your-username.github.io/your-repository/song2.mp3"
    },
    {
        "title": "Song 5",
        "artist": "Artist 5",
        "url": "https://your-username.github.io/your-repository/song2.mp3"
    }
    
]
